terratalk/__init__.py
terratalk/__main__.py
terratalk/terraform_out.py
terratalk/drivers/__init__.py
terratalk/drivers/base.py
terratalk/drivers/bitbucket_cloud_comment.py
terratalk/drivers/bitbucket_server_comment.py
terratalk/drivers/gitea_comment.py
terratalk/drivers/github_comment.py
terratalk/drivers/gitlab_comment.py
terratalk-0.5.1.dist-info/LICENSE
terratalk-0.5.1.dist-info/METADATA
terratalk-0.5.1.dist-info/WHEEL
terratalk-0.5.1.dist-info/entry_points.txt
terratalk-0.5.1.dist-info/top_level.txt
terratalk-0.5.1.dist-info/RECORD
