Metadata-Version: 2.2
Name: terratalk
Version: 0.5.1
Summary: A Terraform commentator.
Home-page: https://github.com/lifeofguenter/terratalk
Author: Günter Grodotzki
Author-email: gunter@grodotzki.com
Classifier: Programming Language :: Python :: 3
Classifier: License :: OSI Approved :: MIT License
Classifier: Operating System :: OS Independent
Requires-Python: >=3
License-File: LICENSE
Requires-Dist: Click
Requires-Dist: requests
Provides-Extra: github
Requires-Dist: PyGithub; extra == "github"
Provides-Extra: gitlab
Requires-Dist: python-gitlab; extra == "gitlab"
Dynamic: author
Dynamic: author-email
Dynamic: classifier
Dynamic: description
Dynamic: description-content-type
Dynamic: home-page
Dynamic: provides-extra
Dynamic: requires-dist
Dynamic: requires-python
Dynamic: summary
